oneTest/test1.py
oneTest/test2.py
oneTest-0.0.0.2.dist-info/METADATA
oneTest-0.0.0.2.dist-info/WHEEL
oneTest-0.0.0.2.dist-info/top_level.txt
oneTest-0.0.0.2.dist-info/RECORD
