Metadata-Version: 2.1
Name: oneTest
Version: 0.0.0.2
Summary: My First Test Package
Home-page: https://lingua.blog.me/...
Author: JieunKim
Author-email: tkdls2024@gmail.com
License: MIT
Platform: UNKNOWN
Requires-Python: >=3
